quickbmsgui/__init__.py
quickbmsgui/main.py
quickbmsgui/tools/__init__.py
quickbmsgui/tools/quickbms_4gb_files.exe
quickbmsgui-0.1.2.dist-info/entry_points.txt
quickbmsgui-0.1.2.dist-info/METADATA
quickbmsgui-0.1.2.dist-info/WHEEL
quickbmsgui-0.1.2.dist-info/RECORD
